pandoc_latex_environment/__init__.py
pandoc_latex_environment/_main.py
pandoc_latex_environment-1.2.1.0.dist-info/METADATA
pandoc_latex_environment-1.2.1.0.dist-info/WHEEL
pandoc_latex_environment-1.2.1.0.dist-info/entry_points.txt
pandoc_latex_environment-1.2.1.0.dist-info/licenses/LICENSE
pandoc_latex_environment-1.2.1.0.dist-info/RECORD
